crabbit/__init__.py
crabbit/__main__.py
crabbit/download.py
crabbit/launcher.py
crabbit/merge.py
crabbit/utils.py
crabbit/vpop.py
jinko_helpers/__init__.py
jinko_helpers/__version__.py
jinko_helpers/calibration.py
jinko_helpers/data_table.py
jinko_helpers/deprecation.py
jinko_helpers/jinko_helpers.py
jinko_helpers/model.py
jinko_helpers/trial.py
jinko_helpers/types/__init__.py
jinko_helpers/types/api_types_dict.py
jinko_helpers/types/deprecated_operations.py
jinko_helpers/types/tags.py
jinko_helpers/vpop.py
jinko_nn/__init__.py
jinko_nn/calibration/__init__.py
jinko_nn/calibration/inn.py
jinko_nn/calibration/inn_calibrator.py
jinko_nn/calibration/utils/data.py
jinko_nn/calibration/utils/layers.py
jinko_nn/calibration/utils/nn.py
jinko_nn/calibration/utils/train.py
jinko_nn/dependencies/dependency_checker.py
jinko_stats/__init__.py
jinko_stats/sample_size.py
jinko_sdk-0.5.8.dist-info/METADATA
jinko_sdk-0.5.8.dist-info/WHEEL
jinko_sdk-0.5.8.dist-info/licenses/LICENSE
jinko_sdk-0.5.8.dist-info/RECORD
