Metadata-Version: 2.4
Name: jinko-sdk
Version: 0.5.8
Summary: A Python package containing jinko_helpers, jinko_stats, and crabbit modules aimed to be used with Jinko.ai API
License-File: LICENSE
Author: SSE Team
Author-email: oss@novainsilico.ai
Requires-Python: >=3.10,<4.0
Classifier: Programming Language :: Python :: 3
Classifier: Programming Language :: Python :: 3.10
Classifier: Programming Language :: Python :: 3.11
Classifier: Programming Language :: Python :: 3.12
Classifier: Programming Language :: Python :: 3.13
Classifier: Programming Language :: Python :: 3.14
Provides-Extra: jinko-nn
Requires-Dist: cma (>=4.4.1,<5.0.0)
Requires-Dist: freia (>=0.2,<0.3) ; extra == "jinko-nn"
Requires-Dist: lifelines (>=0.30.0,<0.31.0) ; extra == "jinko-nn"
Requires-Dist: matplotlib (>=3.9.2,<4.0.0)
Requires-Dist: pandas (>=2.2.2,<3.0.0)
Requires-Dist: requests (>=2.25.1,<3.0.0)
Requires-Dist: scikit-learn (>=1.5.2,<2.0.0) ; extra == "jinko-nn"
Requires-Dist: scipy (>=1.15.3,<2.0.0)
Requires-Dist: seaborn (>=0.13.2,<0.14.0)
Requires-Dist: torch (>=2.10.0,<3.0.0) ; (python_version < "3.15") and (extra == "jinko-nn")
Requires-Dist: tqdm (>=4.66.5,<5.0.0)
